{
  "response": [
    {
        "maintainer": "SirRGB",
        "oem": "Nubia",
        "device": "Mini 5G",
        "filename": "crDroidAndroid-11.0-20220609-TP1803-v7.18.zip",
        "download": "https://github.com/SirRGB/releases/releases/download/202206092331-crDroidAndroid-11.0-20220609-TP1803-v7.18/crDroidAndroid-11.0-20220609-TP1803-v7.18.zip",
        "timestamp": 1654809780,
        "md5": "4b499fcf5b4f904001bf4e5f67a099d3",
        "size": 940538486,
        "version": "7.18",
        "buildtype": "Monthly",
        "forum": "https://t.me/+hvji0wWvr9YyN2Ri",
        "gapps": "",
        "firmware": "",
        "modem": "",
        "bootloader": "",
        "recovery": "",
        "paypal": "",
        "telegram": "https://t.me/+hvji0wWvr9YyN2Ri"
    }
  ]
}
